geoscan_arena_sdk/__init__.py
geoscan_arena_sdk/base/geobot.py
geoscan_arena_sdk/base/pioneer.py
geoscan_arena_sdk/robo_aero/pioneer.py
geoscan_arena_sdk/speed_control/pion.py
geoscan_arena_sdk-1.0.5.dist-info/LICENSE
geoscan_arena_sdk-1.0.5.dist-info/METADATA
geoscan_arena_sdk-1.0.5.dist-info/WHEEL
geoscan_arena_sdk-1.0.5.dist-info/top_level.txt
geoscan_arena_sdk-1.0.5.dist-info/RECORD
