Metadata-Version: 2.1
Name: geoscan_arena_sdk
Version: 1.0.5
Summary: Programming tools for programming Geoscan arena robots
Author: Geoscan
Author-email: info@geoscan.aero
License: MIT
Classifier: Programming Language :: Python :: 3
Classifier: License :: OSI Approved :: MIT License
Classifier: Operating System :: OS Independent
Requires-Python: >=3.9
License-File: LICENSE
Requires-Dist: pymavlink ==2.4.37
Requires-Dist: pyserial ==3.5
Requires-Dist: future ==0.18.3
Requires-Dist: requests
Requires-Dist: numpy
